{"cameraMode":{"drawMode":0,"name":"Shaded","section":"Shading Mode"},"sceneLighting":true,"audioPlay":false,"sceneViewState":{"m_AlwaysRefresh":false,"showFog":true,"showSkybox":true,"showFlares":true,"showImageEffects":true,"showParticleSystems":true,"showVisualEffectGraphs":true,"m_FxEnabled":true},"in2DMode":false,"pivot":{"x":108.5,"y":-12.5,"z":118.5},"rotation":{"x":0.559598982334137,"y":0.11280003935098648,"z":-0.07721897214651108,"w":0.8174198269844055},"size":27.430307388305665,"orthographic":false}